byte/__init__.py
byte/_import_utils.py
byte/bootstrap.py
byte/container.py
byte/context.py
byte/core/__init__.py
byte/core/array_store.py
byte/core/cli.py
byte/core/config/config.py
byte/core/event_bus.py
byte/core/exceptions.py
byte/core/logging.py
byte/core/mixins/__init__.py
byte/core/mixins/bootable.py
byte/core/mixins/conditionable.py
byte/core/mixins/configurable.py
byte/core/mixins/eventable.py
byte/core/mixins/injectable.py
byte/core/mixins/user_interactive.py
byte/core/service/base_service.py
byte/core/service_provider.py
byte/core/task_manager.py
byte/core/utils/__init__.py
byte/core/utils/dump.py
byte/core/utils/extract_content_from_message.py
byte/core/utils/extract_json_from_message.py
byte/core/utils/get_language_from_filename.py
byte/core/utils/get_last_message.py
byte/core/utils/list_to_multiline_text.py
byte/core/utils/parse_partial_json.py
byte/core/utils/slugify.py
byte/core/utils/value.py
byte/domain/__init__.py
byte/domain/agent/__init__.py
byte/domain/agent/implementations/ask/agent.py
byte/domain/agent/implementations/ask/command.py
byte/domain/agent/implementations/ask/prompt.py
byte/domain/agent/implementations/base.py
byte/domain/agent/implementations/cleaner/agent.py
byte/domain/agent/implementations/cleaner/prompt.py
byte/domain/agent/implementations/coder/agent.py
byte/domain/agent/implementations/coder/prompt.py
byte/domain/agent/implementations/commit/agent.py
byte/domain/agent/implementations/commit/prompt.py
byte/domain/agent/implementations/conventions/agent.py
byte/domain/agent/implementations/conventions/command.py
byte/domain/agent/implementations/conventions/constants.py
byte/domain/agent/implementations/conventions/prompt.py
byte/domain/agent/implementations/copy/agent.py
byte/domain/agent/implementations/research/agent.py
byte/domain/agent/implementations/research/command.py
byte/domain/agent/implementations/research/prompt.py
byte/domain/agent/implementations/show/__init__.py
byte/domain/agent/implementations/show/agent.py
byte_ai_cli-0.7.1.dist-info/WHEEL
byte_ai_cli-0.7.1.dist-info/entry_points.txt
byte_ai_cli-0.7.1.dist-info/METADATA
byte_ai_cli-0.7.1.dist-info/RECORD
