Metadata-Version: 2.3
Name: byte-ai-cli
Version: 0.7.1
Summary: A human-in-the-loop AI coding agent that keeps you in control.
Classifier: Environment :: Console
Classifier: Intended Audience :: Developers
Classifier: License :: OSI Approved :: Apache Software License
Classifier: Programming Language :: Python :: 3
Classifier: Programming Language :: Python :: 3.10
Classifier: Programming Language :: Python :: 3.11
Classifier: Programming Language :: Python :: 3.12
Classifier: Programming Language :: Python
Classifier: Topic :: Software Development
Requires-Dist: aiosqlite>=0.21.0
Requires-Dist: beautifulsoup4>=4.14.2
Requires-Dist: click>=8.2.1
Requires-Dist: gitpython>=3.1.45
Requires-Dist: markdownify>=1.2.0
Requires-Dist: pathspec>=0.12.1
Requires-Dist: prompt-toolkit>=3.0.52
Requires-Dist: pydantic>=2.11.7
Requires-Dist: pydantic-settings>=2.10.1
Requires-Dist: pydoll-python>=2.8.2
Requires-Dist: pyperclip>=1.11.0
Requires-Dist: python-dotenv>=1.1.1
Requires-Dist: pyyaml>=6.0.2
Requires-Dist: rich>=14.1.0
Requires-Dist: watchfiles>=1.1.0
Requires-Dist: loguru>=0.7.3
Requires-Dist: pygments>=2.19.2
Requires-Dist: langchain>=1.0.3
Requires-Dist: langchain-openai>=1.0.1
Requires-Dist: langchain-anthropic>=1.0.1
Requires-Dist: langchain-google-genai>=3.0.0
Requires-Dist: langgraph>=1.0.2
Requires-Dist: langchain-core>=1.0.2
Requires-Python: >=3.12
Project-URL: Homepage, https://github.com/UseTheFork/byte
